databind/__init__.py
databind/tagline/__init__.py
databind/tagline/dumper.py
databind/tagline/loader.py
databind/tagline/py.typed
databind.tagline-0.1.3.dist-info/LICENSE.txt
databind.tagline-0.1.3.dist-info/METADATA
databind.tagline-0.1.3.dist-info/WHEEL
databind.tagline-0.1.3.dist-info/top_level.txt
databind.tagline-0.1.3.dist-info/RECORD
