Metadata-Version: 2.1
Name: databind.tagline
Version: 0.1.3
Summary: De/serialize strings of comma-separated key-value pairs using Python type hints.
Home-page: https://github.com/NiklasRosenstein/python-databind
Author: Niklas Rosenstein
Author-email: rosensteinniklas@gmail.com
License: MIT
Platform: UNKNOWN
Requires-Python: >=3.5.0,<4.0.0
Requires-Dist: databind.core (<1.0.0,>=0.4.0)
Requires-Dist: databind.json (<1.0.0,>=0.5.0)
Requires-Dist: nr.parsing.core (<1.1.0,>=1.0.0)
